QSort.v
module partition(xin,xout,i,j,loc_in,loc_out,clk,init,complete,read,write);
parameter N = 8;
input clk,init,read,write;
reg[31:0] vec[0:N-1];
input[31:0] xin;
input[31:0] i,j;
input[31:0] loc_in;
output reg[31:0] loc_out,xout;
output reg complete;
reg[31:0] right,left,loc;
reg set;
reg[31:0] temp,count;
reg[3:0] state;
parameter S0=4'b0000,S1=4'b0001,S2=4'b0010,S3=4'b0011,S4=4'b0100,S5=4'b0101,S6=4'b0110,S7=4'b0111,S8=4'b1000;
// always @(posedge init) begin
//     state<=S0;
//     set<=0;
//     loc<=loc_in;
//     complete<=0;
//     left<=i;
//     right<=j;
// end
always @(posedge clk) begin
  if(read && count!=N)begin
  vec[count]<=xin;
  count<=count+1;
  end
  else if(~read && ~write)count<=0;
end
always @(posedge clk) begin
  if(write && count!=N)begin
    xout<=vec[count];
    count=count+1;
  end
end
always @(posedge clk) begin
    case(state)
    S0:begin state<=init?S1:S0; complete<=0;loc<=loc_in;complete<=0;left<=i;right<=j;end
    S1:begin
      complete<=0;
      if(vec[loc]<=vec[right] && loc!=right)state<=S2;
      else if(vec[loc]>vec[right])begin state<=S4;vec[loc]<=vec[right];vec[right]<=vec[loc];loc<=right;end
      else if(loc==right)state<=S3;
    end
    S2:begin
      if(vec[loc]<=vec[right] && loc!=right)begin state<=S2;right<=right-1;end
      else if(vec[loc]>vec[right])begin state<=S4;vec[loc]<=vec[right];vec[right]<=vec[loc];loc<=right;end
      else if(loc==right)state<=S3;
    end
    S3:begin state<=S0;set<=1;complete<=1;loc_out<=loc;end
    S4:begin
      if(vec[loc]>=vec[left] && left!=loc)state<=S5;
      else if(vec[loc]<vec[left])begin state<=S7;vec[loc]<=vec[left];vec[left]<=vec[loc];loc<=left; end
      else if(loc==left)state<=S6;
    end
    S5:begin
      if(vec[loc]>=vec[left] && left!=loc)begin state<=S5;left<=left+1; end
      else if(vec[loc]<vec[left])begin state<=S7;vec[loc]<=vec[left];vec[left]<=vec[loc];loc<=left; end
      else if(loc==left)state<=S6;
    end
    S6:begin state<=init?S0:S6;set<=1;complete<=1;loc_out<=loc;end
    S7:state<=S1;
    endcase
end
endmodule
module stack(clk,val1,val2,push,pop,ret1,ret2,empty);
parameter N = 64;
input[31:0] val1,val2;
input clk,push,pop;
output reg empty;
output reg[31:0] ret1,ret2;
reg[31:0]  counter;
reg[31:0] mem[0:N];
always @(posedge clk) begin
    if(push)begin
        mem[counter]<=val2;
        mem[counter+1]<=val1;
        counter<=counter+2;
    end
    else if(pop && counter!=0)begin
      ret1<=mem[counter-1];
      ret2<=mem[counter-2];
      counter<=counter-2;
    end
end
always @(counter) begin
    empty<=(counter==0);
end
endmodule
module controller(clk,init,size,empty,complete,ret1,ret2,val1,val2,loc,push,pop,init_p,Qcomp);
input clk,init,empty,complete;
input[31:0] ret1,ret2,loc,size;
output reg push,pop,init_p;
output reg[31:0] val1,val2;
output reg Qcomp;
parameter S0=4'b0000,S1=4'b0001,S2=4'b0010,S3=4'b0011,S4=4'b0100,S5=4'b0101,S6=4'b0110,S7=4'b0111,S8=4'b1000,S9=4'b1001,Si=4'b1010;
reg[3:0] state;
reg[31:0]  i,j;
//reg[31:0] loc;
always @(posedge clk) begin
    case(state)
    S0:state<=init?S9:Si;
    Si:state<=init?S0:Si;
    S9:state<=S1;
    S1:state<=empty?S0:S2;
    S2:state<=S3;
    S3:state<=S4;
    S4:state<=complete?S5:S4;
    S5:state<=S6;
    S6:state<=S7;
    S7:state<=S8;
    S8:state<=S1;
    endcase
end
always @(state) begin
    case(state)
    S0:begin push<=1;val1<=0;val2<=size-1;Qcomp<=0;init_p<=0;end
    Si:begin Qcomp<=1;push<=0;end
    S9:begin push<=0;end
    S2:begin pop<=1;push<=0;end
    S3:pop<=0;
    S4:init_p<=1;
    S5:init_p<=0;
    S6:begin if(ret1<(loc-1) && loc>0)begin 
    push<=1;val1<=ret1;val2<=loc-1;end end
    S7:begin if((loc+1)<ret2 && loc[31]==0)begin
      push<=1;val1<=loc+1;val2<=ret2;
    end
    end
    S8:push<=0;
    endcase
end
endmodule
module  QSort(xin,xout,init,clk,Qcomp,read,write);
parameter N=8 ;
input clk,init,read,write;
output Qcomp;
input[31:0] xin;
output[31:0] xout;
wire[31:0] ret1,ret2,val1,val2,out;
wire[31:0] size;
wire init_p,empty,complete,push,pop,c;
assign size=N;
assign c=clk;
controller C(clk,init,size,empty,complete,ret1,ret2,val1,val2,out,push,pop,init_p,Qcomp);
stack S(clk,val1,val2,push,pop,ret1,ret2,empty);
partition P(xin,xout,ret1,ret2,ret1,out,clk,init_p,complete,read,write);
endmodule

Qtest.v
module Qtest;
parameter N=8 ;
reg clk,init,read,write;
reg[31:0] xin;
wire[31:0] xout;
wire Qcomp;
integer i,c;
integer seed=10;
QSort DUT(xin,xout,init,clk,Qcomp,read,write);
initial begin
    clk=0;
    init=0;
    read=0;
    write=0;
    DUT.P.state=4'b0000;
    DUT.C.state=4'b0000;
    DUT.P.set=0;
   // DUT.P.vec[0]=13;DUT.P.vec[1]=2;DUT.P.vec[2]=8;DUT.P.vec[3]=12;DUT.P.vec[4]=1;DUT.P.vec[5]=3;DUT.P.vec[6]=31;DUT.P.vec[7]=22;
    DUT.S.counter=0;
    for(i=0;i<64;i=i+1)begin
      DUT.S.mem[i]=0;
    end
    #10 read=1;
    xin=$urandom(seed)%100;
    for(i=0;i<7;i=i+1)begin
      #10 xin=$urandom(seed)%100;
    end
    //xin=6;#10 xin=2;#10 xin=8;#10 xin=12;#10 xin=1;#10 xin=3;#10 xin=31;#10 xin=22;
    #10 read=0;
    for(c=0;c<N;c=c+1)begin
      $write("%0d ",DUT.P.vec[c]);
    end
    $write("\n");
    #10 init=1;
    #20 init=0;
    #1000 write=1;
    #5000 $finish;
end
always #5 clk=~clk;
initial begin
    $dumpfile("Qtest.vcd");
    $dumpvars(0,Qtest);
end
always @(posedge Qcomp) begin
    for(c=0;c<N;c=c+1)begin
      $write("%0d ",DUT.P.vec[c]);
    end
    $write("\n");
end
endmodule

Qtest.vcd
$date
	Tue Apr 26 09:37:40 2022
$end
$version
	Icarus Verilog
$end
$timescale
	1s
$end
$scope module Qtest $end
$var wire 32 ! xout [31:0] $end
$var wire 1 " Qcomp $end
$var reg 1 # clk $end
$var reg 1 $ init $end
$var reg 1 % read $end
$var reg 1 & write $end
$var reg 32 ' xin [31:0] $end
$var integer 32 ( c [31:0] $end
$var integer 32 ) i [31:0] $end
$var integer 32 * seed [31:0] $end
$scope module DUT $end
$var wire 1 + c $end
$var wire 1 # clk $end
$var wire 1 $ init $end
$var wire 1 % read $end
$var wire 32 , size [31:0] $end
$var wire 1 & write $end
$var wire 32 - xin [31:0] $end
$var wire 32 . xout [31:0] $end
$var wire 32 / val2 [31:0] $end
$var wire 32 0 val1 [31:0] $end
$var wire 32 1 ret2 [31:0] $end
$var wire 32 2 ret1 [31:0] $end
$var wire 1 3 push $end
$var wire 1 4 pop $end
$var wire 32 5 out [31:0] $end
$var wire 1 6 init_p $end
$var wire 1 7 empty $end
$var wire 1 8 complete $end
$var wire 1 " Qcomp $end
$scope module C $end
$var wire 1 # clk $end
$var wire 1 $ init $end
$var wire 32 9 size [31:0] $end
$var wire 32 : ret2 [31:0] $end
$var wire 32 ; ret1 [31:0] $end
$var wire 32 < loc [31:0] $end
$var wire 1 7 empty $end
$var wire 1 8 complete $end
$var reg 1 " Qcomp $end
$var reg 1 6 init_p $end
$var reg 1 4 pop $end
$var reg 1 3 push $end
$var reg 4 = state [3:0] $end
$var reg 32 > val1 [31:0] $end
$var reg 32 ? val2 [31:0] $end
$upscope $end
$scope module P $end
$var wire 1 # clk $end
$var wire 1 6 init $end
$var wire 1 % read $end
$var wire 1 & write $end
$var wire 32 @ xin [31:0] $end
$var wire 32 A loc_in [31:0] $end
$var wire 32 B j [31:0] $end
$var wire 32 C i [31:0] $end
$var reg 1 8 complete $end
$var reg 32 D count [31:0] $end
$var reg 32 E left [31:0] $end
$var reg 32 F loc [31:0] $end
$var reg 32 G loc_out [31:0] $end
$var reg 32 H right [31:0] $end
$var reg 1 I set $end
$var reg 4 J state [3:0] $end
$var reg 32 K xout [31:0] $end
$upscope $end
$scope module S $end
$var wire 1 # clk $end
$var wire 1 4 pop $end
$var wire 1 3 push $end
$var wire 32 L val1 [31:0] $end
$var wire 32 M val2 [31:0] $end
$var reg 32 N counter [31:0] $end
$var reg 1 7 empty $end
$var reg 32 O ret1 [31:0] $end
$var reg 32 P ret2 [31:0] $end
$upscope $end
$upscope $end
$upscope $end
$enddefinitions $end
#0
$dumpvars
bx P
bx O
b0 N
b111 M
b0 L
bx K
b0 J
0I
bx H
bx G
bx F
bx E
bx D
bx C
bx B
bx A
bx @
b111 ?
b0 >
b0 =
bx <
bx ;
bx :
b1000 9
x8
17
06
bx 5
x4
13
bx 2
bx 1
b0 0
b111 /
bx .
bx -
b1000 ,
0+
b1010 *
b1000000 )
bx (
bx '
0&
0%
0$
0#
0"
bx !
$end
#5
b1000 (
03
1"
07
b1010 =
b10 N
b0 D
08
1+
1#
#10
0+
0#
b0 )
b0 '
b0 -
b0 @
b10101000101000000011 *
1%
#15
b1 D
1+
1#
#20
0+
0#
b1 )
b11110 '
b11110 -
b11110 @
b11011011101011010101101101000 *
#25
b10 D
1+
1#
#30
0+
0#
b10 )
b110100 '
b110100 -
b110100 @
b10100010010101101000101001001001 *
#35
b11 D
1+
1#
#40
0+
0#
b11 )
b110001 '
b110001 -
b110001 @
b11101110100110110111000101110110 *
#45
b100 D
1+
1#
#50
0+
0#
b100 )
b1011001 '
b1011001 -
b1011001 @
b1101000101100101101100101111111 *
#55
b101 D
1+
1#
#60
0+
0#
b101 )
b1001111 '
b1001111 -
b1001111 @
b11000101110000101001110110110100 *
#65
b110 D
1+
1#
#70
0+
0#
b110 )
b100001 '
b100001 -
b100001 @
b11011100100011100110110100100101 *
#75
b111 D
1+
1#
#80
0+
0#
b111 )
b1100001 '
b1100001 -
b1100001 @
b1000110101111010100011110100010 *
#85
b1000 D
1+
1#
#90
0+
0#
b1000 (
0%
#95
b0 D
1+
1#
#100
0+
0#
1$
#105
0"
13
b0 =
1+
1#
#110
0+
0#
#115
03
b100 N
b1001 =
1+
1#
#120
0+
0#
0$
#125
b1 =
1+
1#
#130
0+
0#
#135
14
b10 =
1+
1#
#140
0+
0#
#145
04
b11 =
b10 N
b111 1
b111 :
b111 B
b111 P
b0 2
b0 ;
b0 A
b0 C
b0 O
1+
1#
#150
0+
0#
#155
16
b111 H
b0 E
b0 F
b100 =
1+
1#
#160
0+
0#
#165
b1 J
1+
1#
#170
0+
0#
#175
b10 J
1+
1#
#180
0+
0#
#185
b110 H
1+
1#
#190
0+
0#
#195
b101 H
1+
1#
#200
0+
0#
#205
b100 H
1+
1#
#210
0+
0#
#215
b11 H
1+
1#
#220
0+
0#
#225
b10 H
1+
1#
#230
0+
0#
#235
b1 H
1+
1#
#240
0+
0#
#245
b0 H
1+
1#
#250
0+
0#
#255
b11 J
1+
1#
#260
0+
0#
#265
b0 5
b0 <
b0 G
18
1I
b0 J
1+
1#
#270
0+
0#
#275
06
b111 H
08
b1 J
b101 =
1+
1#
#280
0+
0#
#285
b110 =
b10 J
1+
1#
#290
0+
0#
#295
b1 0
b1 >
b1 L
13
b110 H
b111 =
1+
1#
#300
0+
0#
#305
03
b1000 =
b100 N
b101 H
1+
1#
#310
0+
0#
#315
b100 H
b1 =
1+
1#
#320
0+
0#
#325
14
b10 =
b11 H
1+
1#
#330
0+
0#
#335
04
b10 H
b10 N
b1 2
b1 ;
b1 A
b1 C
b1 O
b11 =
1+
1#
#340
0+
0#
#345
16
b100 =
b1 H
1+
1#
#350
0+
0#
#355
b0 H
1+
1#
#360
0+
0#
#365
b11 J
1+
1#
#370
0+
0#
#375
18
b0 J
1+
1#
#380
0+
0#
#385
06
b101 =
b111 H
b1 E
b1 F
08
b1 J
1+
1#
#390
0+
0#
#395
b10 J
b110 =
1+
1#
#400
0+
0#
#405
13
b111 =
b110 H
1+
1#
#410
0+
0#
#415
03
b101 H
b100 N
b1000 =
1+
1#
#420
0+
0#
#425
b1 =
b100 H
1+
1#
#430
0+
0#
#435
14
b11 H
b10 =
1+
1#
#440
0+
0#
#445
04
b11 =
b10 N
b10 H
1+
1#
#450
0+
0#
#455
16
b1 H
b100 =
1+
1#
#460
0+
0#
#465
b11 J
1+
1#
#470
0+
0#
#475
b1 5
b1 <
b1 G
18
b0 J
1+
1#
#480
0+
0#
#485
06
b101 =
b111 H
08
b1 J
1+
1#
#490
0+
0#
#495
b10 J
b110 =
1+
1#
#500
0+
0#
#505
b10 0
b10 >
b10 L
13
b111 =
b110 H
1+
1#
#510
0+
0#
#515
03
b101 H
b100 N
b1000 =
1+
1#
#520
0+
0#
#525
b1 =
b100 H
1+
1#
#530
0+
0#
#535
14
b11 H
b10 =
1+
1#
#540
0+
0#
#545
04
b11 =
b10 N
b10 2
b10 ;
b10 A
b10 C
b10 O
b10 H
1+
1#
#550
0+
0#
#555
16
b1 H
b100 =
1+
1#
#560
0+
0#
#565
b11 J
1+
1#
#570
0+
0#
#575
18
b0 J
1+
1#
#580
0+
0#
#585
06
b101 =
b111 H
b10 E
b10 F
08
b1 J
1+
1#
#590
0+
0#
#595
b10 J
b110 =
1+
1#
#600
0+
0#
#605
13
b111 =
b110 H
1+
1#
#610
0+
0#
#615
03
b110 F
b100 J
b100 N
b1000 =
1+
1#
#620
0+
0#
#625
b1 =
b101 J
1+
1#
#630
0+
0#
#635
14
b11 E
b10 =
1+
1#
#640
0+
0#
#645
04
b11 =
b10 N
b100 E
1+
1#
#650
0+
0#
#655
16
b100 F
b111 J
b100 =
1+
1#
#660
0+
0#
#665
b1 J
1+
1#
#670
0+
0#
#675
b10 J
1+
1#
#680
0+
0#
#685
b101 H
1+
1#
#690
0+
0#
#695
b100 H
1+
1#
#700
0+
0#
#705
b11 J
1+
1#
#710
0+
0#
#715
b100 5
b100 <
b100 G
18
b0 J
1+
1#
#720
0+
0#
#725
06
b101 =
b111 H
b10 E
b10 F
08
b1 J
1+
1#
#730
0+
0#
#735
b11 /
b11 ?
b11 M
13
b10 J
b110 =
1+
1#
#740
0+
0#
#745
b111 /
b111 ?
b111 M
b101 0
b101 >
b101 L
b111 =
b100 N
b110 H
1+
1#
#750
0+
0#
#755
03
b101 H
b110 N
b1000 =
1+
1#
#760
0+
0#
#765
b1 =
b100 H
1+
1#
#770
0+
0#
#775
14
b11 H
b10 =
1+
1#
#780
0+
0#
#785
04
b11 =
b100 N
b101 2
b101 ;
b101 A
b101 C
b101 O
b10 H
1+
1#
#790
0+
0#
#795
16
b11 J
b100 =
1+
1#
#800
0+
0#
#805
b10 5
b10 <
b10 G
18
b0 J
1+
1#
#810
0+
0#
#815
06
b111 H
b101 E
b101 F
08
b1 J
b101 =
1+
1#
#820
0+
0#
#825
b110 =
b10 J
1+
1#
#830
0+
0#
#835
b11 0
b11 >
b11 L
13
b110 H
b111 =
1+
1#
#840
0+
0#
#845
03
b1000 =
b110 N
b101 H
1+
1#
#850
0+
0#
#855
b11 J
b1 =
1+
1#
#860
0+
0#
#865
14
b10 =
b101 5
b101 <
b101 G
18
b0 J
1+
1#
#870
0+
0#
#875
04
b111 H
08
b100 N
b11 2
b11 ;
b11 A
b11 C
b11 O
b11 =
1+
1#
#880
0+
0#
#885
16
b100 =
b11 E
b11 F
1+
1#
#890
0+
0#
#895
b1 J
1+
1#
#900
0+
0#
#905
b10 J
1+
1#
#910
0+
0#
#915
b110 H
1+
1#
#920
0+
0#
#925
b101 H
1+
1#
#930
0+
0#
#935
b100 H
1+
1#
#940
0+
0#
#945
b11 H
1+
1#
#950
0+
0#
#955
b11 J
1+
1#
#960
0+
0#
#965
b11 5
b11 <
b11 G
18
b0 J
1+
1#
#970
0+
0#
#975
06
b111 H
08
b1 J
b101 =
1+
1#
#980
0+
0#
#985
b110 =
b10 J
1+
1#
#990
0+
0#
#995
b100 0
b100 >
b100 L
13
b110 H
b111 =
1+
1#
#1000
0+
0#
#1005
03
b1000 =
b110 N
b101 H
1+
1#
#1010
0+
0#
#1015
b100 H
b1 =
1+
1#
#1020
0+
0#
#1025
14
b10 =
b11 H
1+
1#
#1030
0+
0#
#1035
04
b11 J
b100 N
b100 2
b100 ;
b100 A
b100 C
b100 O
b11 =
1+
1#
#1040
0+
0#
#1045
16
b100 =
18
b0 J
1+
1#
#1050
0+
0#
#1055
06
b111 H
b100 E
b100 F
08
b1 J
b101 =
1+
1#
#1060
0+
0#
#1065
b110 =
b10 J
1+
1#
#1070
0+
0#
#1075
13
b110 H
b111 =
1+
1#
#1080
0+
0#
#1085
03
b1000 =
b110 N
b101 H
1+
1#
#1090
0+
0#
#1095
b100 H
b1 =
1+
1#
#1100
0+
0#
#1105
14
b10 =
b11 J
1+
1#
#1110
0+
0#
#1115
04
b100 5
b100 <
b100 G
18
b0 J
b100 N
b11 =
1+
1#
#1120
0+
0#
1&
#1125
16
b100 =
b0 !
b0 .
b0 K
b111 H
08
b1 D
1+
1#
#1130
0+
0#
#1135
b1 J
b11110 !
b11110 .
b11110 K
b10 D
1+
1#
#1140
0+
0#
#1145
b100001 !
b100001 .
b100001 K
b10 J
b11 D
1+
1#
#1150
0+
0#
#1155
b110 H
b110001 !
b110001 .
b110001 K
b100 D
1+
1#
#1160
0+
0#
#1165
b110100 !
b110100 .
b110100 K
b101 H
b101 D
1+
1#
#1170
0+
0#
#1175
b100 H
b1001111 !
b1001111 .
b1001111 K
b110 D
1+
1#
#1180
0+
0#
#1185
b1011001 !
b1011001 .
b1011001 K
b11 J
b111 D
1+
1#
#1190
0+
0#
#1195
18
b0 J
b1100001 !
b1100001 .
b1100001 K
b1000 D
1+
1#
#1200
0+
0#
#1205
06
b101 =
b111 H
08
b1 J
1+
1#
#1210
0+
0#
#1215
b10 J
b110 =
1+
1#
#1220
0+
0#
#1225
b101 0
b101 >
b101 L
13
b111 =
b110 H
1+
1#
#1230
0+
0#
#1235
03
b101 H
b110 N
b1000 =
1+
1#
#1240
0+
0#
#1245
b1 =
b100 H
1+
1#
#1250
0+
0#
#1255
14
b11 J
b10 =
1+
1#
#1260
0+
0#
#1265
04
b11 =
b100 N
b101 2
b101 ;
b101 A
b101 C
b101 O
18
b0 J
1+
1#
#1270
0+
0#
#1275
16
b111 H
b101 E
b101 F
08
b100 =
1+
1#
#1280
0+
0#
#1285
b1 J
1+
1#
#1290
0+
0#
#1295
b10 J
1+
1#
#1300
0+
0#
#1305
b110 H
1+
1#
#1310
0+
0#
#1315
b101 H
1+
1#
#1320
0+
0#
#1325
b11 J
1+
1#
#1330
0+
0#
#1335
b101 5
b101 <
b101 G
18
b0 J
1+
1#
#1340
0+
0#
#1345
06
b101 =
b111 H
08
b1 J
1+
1#
#1350
0+
0#
#1355
b10 J
b110 =
1+
1#
#1360
0+
0#
#1365
b110 0
b110 >
b110 L
13
b111 =
b110 H
1+
1#
#1370
0+
0#
#1375
03
b101 H
b110 N
b1000 =
1+
1#
#1380
0+
0#
#1385
b1 =
b11 J
1+
1#
#1390
0+
0#
#1395
14
18
b0 J
b10 =
1+
1#
#1400
0+
0#
#1405
04
b11 =
b100 N
b110 2
b110 ;
b110 A
b110 C
b110 O
b111 H
08
1+
1#
#1410
0+
0#
#1415
16
b110 E
b110 F
b100 =
1+
1#
#1420
0+
0#
#1425
b1 J
1+
1#
#1430
0+
0#
#1435
b10 J
1+
1#
#1440
0+
0#
#1445
b110 H
1+
1#
#1450
0+
0#
#1455
b11 J
1+
1#
#1460
0+
0#
#1465
b110 5
b110 <
b110 G
18
b0 J
1+
1#
#1470
0+
0#
#1475
06
b111 H
08
b1 J
b101 =
1+
1#
#1480
0+
0#
#1485
b110 =
b10 J
1+
1#
#1490
0+
0#
#1495
b110 H
b111 =
1+
1#
#1500
0+
0#
#1505
b1000 =
b11 J
1+
1#
#1510
0+
0#
#1515
18
b0 J
b1 =
1+
1#
#1520
0+
0#
#1525
14
b10 =
b111 H
08
1+
1#
#1530
0+
0#
#1535
04
b10 N
b11 1
b11 :
b11 B
b11 P
b10 2
b10 ;
b10 A
b10 C
b10 O
b11 =
1+
1#
#1540
0+
0#
#1545
16
b100 =
b11 H
b10 E
b10 F
1+
1#
#1550
0+
0#
#1555
b1 J
1+
1#
#1560
0+
0#
#1565
b10 J
1+
1#
#1570
0+
0#
#1575
b10 H
1+
1#
#1580
0+
0#
#1585
b11 J
1+
1#
#1590
0+
0#
#1595
b10 5
b10 <
b10 G
18
b0 J
1+
1#
#1600
0+
0#
#1605
06
b101 =
b11 H
08
b1 J
1+
1#
#1610
0+
0#
#1615
b10 J
b110 =
1+
1#
#1620
0+
0#
#1625
b111 =
b10 H
1+
1#
#1630
0+
0#
#1635
b11 J
b1000 =
1+
1#
#1640
0+
0#
#1645
b1 =
18
b0 J
1+
1#
#1650
0+
0#
#1655
14
b11 H
08
b10 =
1+
1#
#1660
0+
0#
#1665
04
17
b11 =
b0 N
b111 1
b111 :
b111 B
b111 P
b0 2
b0 ;
b0 A
b0 C
b0 O
1+
1#
#1670
0+
0#
#1675
16
b111 H
b0 E
b0 F
b100 =
1+
1#
#1680
0+
0#
#1685
b1 J
1+
1#
#1690
0+
0#
#1695
b10 J
1+
1#
#1700
0+
0#
#1705
b110 H
1+
1#
#1710
0+
0#
#1715
b101 H
1+
1#
#1720
0+
0#
#1725
b100 H
1+
1#
#1730
0+
0#
#1735
b11 H
1+
1#
#1740
0+
0#
#1745
b10 H
1+
1#
#1750
0+
0#
#1755
b1 H
1+
1#
#1760
0+
0#
#1765
b0 H
1+
1#
#1770
0+
0#
#1775
b11 J
1+
1#
#1780
0+
0#
#1785
b0 5
b0 <
b0 G
18
b0 J
1+
1#
#1790
0+
0#
#1795
06
b111 H
08
b1 J
b101 =
1+
1#
#1800
0+
0#
#1805
b110 =
b10 J
1+
1#
#1810
0+
0#
#1815
b1 0
b1 >
b1 L
13
b110 H
b111 =
1+
1#
#1820
0+
0#
#1825
03
07
b1000 =
b10 N
b101 H
1+
1#
#1830
0+
0#
#1835
b100 H
b1 =
1+
1#
#1840
0+
0#
#1845
14
b10 =
b11 H
1+
1#
#1850
0+
0#
#1855
17
04
b10 H
b0 N
b1 2
b1 ;
b1 A
b1 C
b1 O
b11 =
1+
1#
#1860
0+
0#
#1865
16
b100 =
b1 H
1+
1#
#1870
0+
0#
#1875
b0 H
1+
1#
#1880
0+
0#
#1885
b11 J
1+
1#
#1890
0+
0#
#1895
18
b0 J
1+
1#
#1900
0+
0#
#1905
06
b101 =
b111 H
b1 E
b1 F
08
b1 J
1+
1#
#1910
0+
0#
#1915
b10 J
b110 =
1+
1#
#1920
0+
0#
#1925
13
b111 =
b110 H
1+
1#
#1930
0+
0#
#1935
07
03
b101 H
b10 N
b1000 =
1+
1#
#1940
0+
0#
#1945
b1 =
b100 H
1+
1#
#1950
0+
0#
#1955
14
b11 H
b10 =
1+
1#
#1960
0+
0#
#1965
04
17
b11 =
b0 N
b10 H
1+
1#
#1970
0+
0#
#1975
16
b1 H
b100 =
1+
1#
#1980
0+
0#
#1985
b11 J
1+
1#
#1990
0+
0#
#1995
b1 5
b1 <
b1 G
18
b0 J
1+
1#
#2000
0+
0#
#2005
06
b101 =
b111 H
08
b1 J
1+
1#
#2010
0+
0#
#2015
b10 J
b110 =
1+
1#
#2020
0+
0#
#2025
b10 0
b10 >
b10 L
13
b111 =
b110 H
1+
1#
#2030
0+
0#
#2035
07
03
b101 H
b10 N
b1000 =
1+
1#
#2040
0+
0#
#2045
b1 =
b100 H
1+
1#
#2050
0+
0#
#2055
14
b11 H
b10 =
1+
1#
#2060
0+
0#
#2065
04
17
b11 =
b0 N
b10 2
b10 ;
b10 A
b10 C
b10 O
b10 H
1+
1#
#2070
0+
0#
#2075
16
b1 H
b100 =
1+
1#
#2080
0+
0#
#2085
b11 J
1+
1#
#2090
0+
0#
#2095
18
b0 J
1+
1#
#2100
0+
0#
#2105
06
b101 =
b111 H
b10 E
b10 F
08
b1 J
1+
1#
#2110
0+
0#
#2115
b10 J
b110 =
1+
1#
#2120
0+
0#
#2125
13
b111 =
b110 H
1+
1#
#2130
0+
0#
#2135
07
03
b101 H
b10 N
b1000 =
1+
1#
#2140
0+
0#
#2145
b1 =
b100 H
1+
1#
#2150
0+
0#
#2155
14
b11 H
b10 =
1+
1#
#2160
0+
0#
#2165
04
17
b11 =
b0 N
b10 H
1+
1#
#2170
0+
0#
#2175
16
b11 J
b100 =
1+
1#
#2180
0+
0#
#2185
b10 5
b10 <
b10 G
18
b0 J
1+
1#
#2190
0+
0#
#2195
06
b111 H
08
b1 J
b101 =
1+
1#
#2200
0+
0#
#2205
b110 =
b10 J
1+
1#
#2210
0+
0#
#2215
b11 0
b11 >
b11 L
13
b110 H
b111 =
1+
1#
#2220
0+
0#
#2225
03
07
b1000 =
b10 N
b101 H
1+
1#
#2230
0+
0#
#2235
b100 H
b1 =
1+
1#
#2240
0+
0#
#2245
14
b10 =
b11 H
1+
1#
#2250
0+
0#
#2255
17
04
b10 H
b0 N
b11 2
b11 ;
b11 A
b11 C
b11 O
b11 =
1+
1#
#2260
0+
0#
#2265
16
b100 =
b11 J
1+
1#
#2270
0+
0#
#2275
18
b0 J
1+
1#
#2280
0+
0#
#2285
06
b101 =
b111 H
b11 E
b11 F
08
b1 J
1+
1#
#2290
0+
0#
#2295
b10 J
b110 =
1+
1#
#2300
0+
0#
#2305
13
b111 =
b110 H
1+
1#
#2310
0+
0#
#2315
07
03
b101 H
b10 N
b1000 =
1+
1#
#2320
0+
0#
#2325
b1 =
b100 H
1+
1#
#2330
0+
0#
#2335
14
b11 H
b10 =
1+
1#
#2340
0+
0#
#2345
04
17
b11 =
b0 N
b11 J
1+
1#
#2350
0+
0#
#2355
16
b11 5
b11 <
b11 G
18
b0 J
b100 =
1+
1#
#2360
0+
0#
#2365
06
b101 =
b111 H
08
b1 J
1+
1#
#2370
0+
0#
#2375
b10 J
b110 =
1+
1#
#2380
0+
0#
#2385
b100 0
b100 >
b100 L
13
b111 =
b110 H
1+
1#
#2390
0+
0#
#2395
07
03
b101 H
b10 N
b1000 =
1+
1#
#2400
0+
0#
#2405
b1 =
b100 H
1+
1#
#2410
0+
0#
#2415
14
b11 H
b10 =
1+
1#
#2420
0+
0#
#2425
04
17
b11 =
b0 N
b100 2
b100 ;
b100 A
b100 C
b100 O
b11 J
1+
1#
#2430
0+
0#
#2435
16
18
b0 J
b100 =
1+
1#
#2440
0+
0#
#2445
06
b101 =
b111 H
b100 E
b100 F
08
b1 J
1+
1#
#2450
0+
0#
#2455
b10 J
b110 =
1+
1#
#2460
0+
0#
#2465
13
b111 =
b110 H
1+
1#
#2470
0+
0#
#2475
07
03
b101 H
b10 N
b1000 =
1+
1#
#2480
0+
0#
#2485
b1 =
b100 H
1+
1#
#2490
0+
0#
#2495
14
b11 J
b10 =
1+
1#
#2500
0+
0#
#2505
04
17
b11 =
b0 N
b100 5
b100 <
b100 G
18
b0 J
1+
1#
#2510
0+
0#
#2515
16
b111 H
08
b100 =
1+
1#
#2520
0+
0#
#2525
b1 J
1+
1#
#2530
0+
0#
#2535
b10 J
1+
1#
#2540
0+
0#
#2545
b110 H
1+
1#
#2550
0+
0#
#2555
b101 H
1+
1#
#2560
0+
0#
#2565
b100 H
1+
1#
#2570
0+
0#
#2575
b11 J
1+
1#
#2580
0+
0#
#2585
18
b0 J
1+
1#
#2590
0+
0#
#2595
06
b111 H
08
b1 J
b101 =
1+
1#
#2600
0+
0#
#2605
b110 =
b10 J
1+
1#
#2610
0+
0#
#2615
b101 0
b101 >
b101 L
13
b110 H
b111 =
1+
1#
#2620
0+
0#
#2625
03
07
b1000 =
b10 N
b101 H
1+
1#
#2630
0+
0#
#2635
b100 H
b1 =
1+
1#
#2640
0+
0#
#2645
14
b10 =
b11 J
1+
1#
#2650
0+
0#
#2655
17
04
18
b0 J
b0 N
b101 2
b101 ;
b101 A
b101 C
b101 O
b11 =
1+
1#
#2660
0+
0#
#2665
16
b100 =
b111 H
b101 E
b101 F
08
1+
1#
#2670
0+
0#
#2675
b1 J
1+
1#
#2680
0+
0#
#2685
b10 J
1+
1#
#2690
0+
0#
#2695
b110 H
1+
1#
#2700
0+
0#
#2705
b101 H
1+
1#
#2710
0+
0#
#2715
b11 J
1+
1#
#2720
0+
0#
#2725
b101 5
b101 <
b101 G
18
b0 J
1+
1#
#2730
0+
0#
#2735
06
b111 H
08
b1 J
b101 =
1+
1#
#2740
0+
0#
#2745
b110 =
b10 J
1+
1#
#2750
0+
0#
#2755
b110 0
b110 >
b110 L
13
b110 H
b111 =
1+
1#
#2760
0+
0#
#2765
03
07
b1000 =
b10 N
b101 H
1+
1#
#2770
0+
0#
#2775
b11 J
b1 =
1+
1#
#2780
0+
0#
#2785
14
b10 =
18
b0 J
1+
1#
#2790
0+
0#
#2795
17
04
b111 H
08
b0 N
b110 2
b110 ;
b110 A
b110 C
b110 O
b11 =
1+
1#
#2800
0+
0#
#2805
16
b100 =
b110 E
b110 F
1+
1#
#2810
0+
0#
#2815
b1 J
1+
1#
#2820
0+
0#
#2825
b10 J
1+
1#
#2830
0+
0#
#2835
b110 H
1+
1#
#2840
0+
0#
#2845
b11 J
1+
1#
#2850
0+
0#
#2855
b110 5
b110 <
b110 G
18
b0 J
1+
1#
#2860
0+
0#
#2865
06
b101 =
b111 H
08
b1 J
1+
1#
#2870
0+
0#
#2875
b10 J
b110 =
1+
1#
#2880
0+
0#
#2885
b111 =
b110 H
1+
1#
#2890
0+
0#
#2895
b11 J
b1000 =
1+
1#
#2900
0+
0#
#2905
b1 =
18
b0 J
1+
1#
#2910
0+
0#
